elderscrollslegendssdk
tests
