Metadata-Version: 1.1
Name: elderscrollslegendssdk
Version: 1.1.0
Summary: Elder Scrolls: Legends SDK for https://elderscrollslegends.io
Home-page: https://github.com/ElderScrollsLegends/elder-scrolls-legends-sdk-python
Author: Andrew Backes
Author-email: backes.andrew@gmail.com
License: MIT
Download-URL: https://github.com/ElderScrollsLegends/elder-scrolls-legends-sdk-python/tarball/1.1.0
Keywords: elder scrolls legends tcg sdk trading card game api rest
Platform: UNKNOWN
Classifier: Development Status :: 4 - Beta
Classifier: Intended Audience :: Developers
Classifier: License :: OSI Approved :: MIT License
Classifier: Natural Language :: English
Classifier: Operating System :: Unix
Classifier: Programming Language :: Python :: 3.6
Classifier: Operating System :: OS Independent
